crashlog/__init__.py
crashlog/admin.py
crashlog/config.py
crashlog/middleware.py
crashlog/models.py
crashlog/migrations/0001_initial.py
crashlog/migrations/__init__.py
crashlog/templates/admin/crashlog/error_form.html
django_crashlog-1.2.0.dist-info/METADATA
django_crashlog-1.2.0.dist-info/WHEEL
django_crashlog-1.2.0.dist-info/top_level.txt
django_crashlog-1.2.0.dist-info/RECORD
