Metadata-Version: 2.1
Name: django-crashlog
Version: 1.2.0
Summary: Django Database Exception Logger
Home-page: https://github.com/saxix/django-strategy-field
Author: sax
Author-email: sax@os4d.org
License: BSD
Platform: linux
Classifier: Environment :: Web Environment
Classifier: Framework :: Django
Classifier: Framework :: Django :: 2.2
Classifier: Framework :: Django :: 3.2
Classifier: Framework :: Django :: 4.0
Classifier: Operating System :: OS Independent
Classifier: Programming Language :: Python :: 3.8
Classifier: Programming Language :: Python :: 3.9
Classifier: Programming Language :: Python :: 3.10
Classifier: Intended Audience :: Developers
Requires-Dist: django-admin-extra-urls
Provides-Extra: dev
Requires-Dist: flake8 ; extra == 'dev'
Requires-Dist: django-webtest ; extra == 'dev'
Requires-Dist: pytest-cache ; extra == 'dev'
Requires-Dist: pytest-cov ; extra == 'dev'
Requires-Dist: pytest-django ; extra == 'dev'
Requires-Dist: pytest-echo ; extra == 'dev'
Requires-Dist: pytest-pythonpath ; extra == 'dev'
Requires-Dist: pytest ; extra == 'dev'
Requires-Dist: psycopg2 ; extra == 'dev'
Requires-Dist: pdbpp ; extra == 'dev'
Provides-Extra: test
Requires-Dist: flake8 ; extra == 'test'
Requires-Dist: django-webtest ; extra == 'test'
Requires-Dist: pytest-cache ; extra == 'test'
Requires-Dist: pytest-cov ; extra == 'test'
Requires-Dist: pytest-django ; extra == 'test'
Requires-Dist: pytest-echo ; extra == 'test'
Requires-Dist: pytest-pythonpath ; extra == 'test'
Requires-Dist: pytest ; extra == 'test'
Requires-Dist: psycopg2 ; extra == 'test'
Requires-Dist: pdbpp ; extra == 'test'
